<?xml version="1.0" encoding="UTF-8"?>
<root type="DungeonActPrototype">
<act pid="10111" name="天庭" nameIcon="TheFuBenUI|1" iconName="HeroItem|hero_02" backgroundName="TheFuBenUI_NoAlpha|point_02" desc="有些东西失去了，比拥有更刻骨铭心。 " descName="——齐天大圣" includeDungeon="10101,10102,10103,10104,10105,10106,10107" openLevel="0" reward="-1|100053=5000,10174=25;-1|100053=10000,10174=50;7|100053=20000,100054=120,10172=1" storyID="0" maxStar="7" nextID="10112" dungenonOrder="1" backID="0" soundID="1031204"/>
<act pid="10112" name="花果山" nameIcon="TheFuBenUI|2" iconName="HeroItem|monster_14" backgroundName="TheFuBenUI_NoAlpha|point_06" desc="一段奋不顾身的爱情，一次说走就走的旅行" descName="——唐僧" includeDungeon="10108,10109,101010,101011,101012,101013,101014" openLevel="0" reward="-1|100053=5000,10174=25;-1|100053=10000,10174=50;7|100053=40000,100054=150,10172=1" storyID="0" maxStar="7" nextID="10113" dungenonOrder="2" backID="10111" soundID="1031201"/>
<act pid="10113" name="傲来国" nameIcon="TheFuBenUI|3" iconName="HeroItem|hero_06" backgroundName="TheFuBenUI_NoAlpha|point_03" desc="人如果没有理想，那跟咸鱼有什么区别" descName="——孙悟空" includeDungeon="101015,101016,101017,101018,101019,101020,101021,101022" openLevel="0" reward="-1|100053=5000,10174=25;8|100053=60000,10172=1;16|100054=200,10174=25,10172=1,10173=3" storyID="0" maxStar="16" nextID="10114" dungenonOrder="3" backID="10112" soundID="1031203"/>
<act pid="10114" name="高老庄" nameIcon="TheFuBenUI|4" iconName="HeroItem|hero_07" backgroundName="TheFuBenUI_NoAlpha|point_04" desc="我冲开枷锁，不顾一切，只希望你能看见我" descName="——猪八戒" includeDungeon="101023,101024,101025,101026,101027,101028,101029,101030,101031,101032" openLevel="0" reward="10|100053=80000,10172=1;20|10172=1,10173=3;30|100054=200,10174=30" storyID="0" maxStar="30" nextID="10115" dungenonOrder="4" backID="10113" soundID="103199"/>
<act pid="10115" name="流沙河" nameIcon="TheFuBenUI|5" iconName="HeroItem|hero_08" backgroundName="TheFuBenUI_NoAlpha|point_05" desc="如果我不曾见过阳光我本可以忍受黑暗" descName="——沙和尚" includeDungeon="101033,101034,101035,101036,101037,101038,101039,101040,101041,101042" openLevel="0" reward="10|100053=100000,10020245=1,10172=1;20|10173=3,10174=35,10172=1;30|100054=200,10174=60,101412=1" storyID="0" maxStar="30" nextID="10116" dungenonOrder="5" backID="10114" soundID="1031204"/>
<act pid="10116" name="黄风岭（上）" nameIcon="TheFuBenUI|6" iconName="HeroItem|hero_154" backgroundName="TheFuBenUI_NoAlpha|point_06" desc="你猜" descName="——你猜" includeDungeon="101043,101044,101045,101046,101047,101048,101049,101050,101051,101052" openLevel="0" reward="10|100053=120000,10172=1;20|10173=3,10174=40,10172=1;30|100054=200,10174=70,10172=1" storyID="0" maxStar="30" nextID="10117" dungenonOrder="6" backID="10115" soundID="1031201"/>
<act pid="10117" name="黄风岭（下）" nameIcon="TheFuBenUI|7" iconName="HeroItem|hero_154" backgroundName="TheFuBenUI_NoAlpha|point_07" desc="你猜" descName="——你猜" includeDungeon="101053,101054,101055,101056,101057,101058,101059,101060,101061,101062" openLevel="0" reward="10|100053=140000,10172=1;20|10173=3,10174=45,10172=1;30|100054=200,10174=80,10172=1" storyID="0" maxStar="30" nextID="10118" dungenonOrder="7" backID="10116" soundID="1031203"/>
<act pid="10118" name="宝象国（上）" nameIcon="TheFuBenUI|8" iconName="HeroItem|hero_134" backgroundName="TheFuBenUI_NoAlpha|point_08" desc="你猜" descName="——你猜" includeDungeon="101063,101064,101065,101066,101067,101068,101069,101070,101071,101072" openLevel="0" reward="10|100053=160000,10172=1;20|10173=3,10174=50,10172=1;30|100054=200,10174=90,10172=1" storyID="0" maxStar="30" nextID="10119" dungenonOrder="8" backID="10117" soundID="103199"/>
<act pid="10119" name="宝象国（下）" nameIcon="TheFuBenUI|9" iconName="HeroItem|hero_134" backgroundName="TheFuBenUI_NoAlpha|point_09" desc="你猜" descName="——你猜" includeDungeon="101073,101074,101075,101076,101077,101078,101079,101080,101081,101082" openLevel="0" reward="10|100053=180000,10172=1;20|10173=3,10174=55,10172=1;30|100054=200,10174=100,10172=1" storyID="0" maxStar="30" nextID="101110" dungenonOrder="9" backID="10118" soundID="1031204"/>
<act pid="101110" name="平顶山（上）" nameIcon="TheFuBenUI|22" iconName="HeroItem|hero_34" backgroundName="TheFuBenUI_NoAlpha|point_10" desc="你猜" descName="——你猜" includeDungeon="101083,101084,101085,101086,101087,101088,101089,101090,101091,101092" openLevel="0" reward="10|100053=200000,10172=1;20|10173=3,10174=60,10172=1;30|100054=200,10174=110,10172=1" storyID="0" maxStar="30" nextID="101111" dungenonOrder="10" backID="10119" soundID="1031201"/>
<act pid="101111" name="平顶山（中）" nameIcon="TheFuBenUI|23" iconName="HeroItem|hero_34" backgroundName="TheFuBenUI_NoAlpha|point_11" desc="你猜" descName="——你猜" includeDungeon="101093,101094,101095,101096,101097,101098,101099,1010100,1010101,1010102" openLevel="0" reward="10|100053=220000,10172=1;20|10173=3,10174=65,10172=1;30|100054=200,10174=120,10172=1" storyID="0" maxStar="30" nextID="101112" dungenonOrder="11" backID="101110" soundID="1031203"/>
<act pid="101112" name="平顶山（下）" nameIcon="TheFuBenUI|24" iconName="HeroItem|hero_76" backgroundName="TheFuBenUI_NoAlpha|point_12" desc="你猜" descName="——你猜" includeDungeon="1010103,1010104,1010105,1010106,1010107,1010108,1010109,1010110,1010111,1010112" openLevel="0" reward="10|100053=240000,10172=1;20|10173=3,10174=70,10172=1;30|100054=200,10174=130,10172=1" storyID="0" maxStar="30" nextID="101113" dungenonOrder="12" backID="101111" soundID="103199"/>
<act pid="101113" name="压龙山（上）" nameIcon="TheFuBenUI|10" iconName="HeroItem|hero_124" backgroundName="TheFuBenUI_NoAlpha|point_13" desc="你猜" descName="——你猜" includeDungeon="1010113,1010114,1010115,1010116,1010117,1010118,1010119,1010120,1010121,1010122" openLevel="0" reward="10|100053=260000,10172=1;20|10173=3,10174=75,10172=1;30|100054=200,10174=140,10172=1" storyID="0" maxStar="30" nextID="101114" dungenonOrder="13" backID="101112" soundID="1031204"/>
<act pid="101114" name="压龙山（中）" nameIcon="TheFuBenUI|11" iconName="HeroItem|monster_11" backgroundName="TheFuBenUI_NoAlpha|point_01" desc="你猜" descName="——你猜" includeDungeon="1010123,1010124,1010125,1010126,1010127,1010128,1010129,1010130,1010131,1010132" openLevel="0" reward="10|100053=280000,10172=1;20|10173=3,10174=80,10172=1;30|100054=200,10174=150,10172=1" storyID="0" maxStar="30" nextID="101115" dungenonOrder="14" backID="101113" soundID="1031201"/>
<act pid="101115" name="压龙山（下）" nameIcon="TheFuBenUI|12" iconName="HeroItem|hero_38" backgroundName="TheFuBenUI_NoAlpha|point_02" desc="你猜" descName="——你猜" includeDungeon="1010133,1010134,1010135,1010136,1010137,1010138,1010139,1010140,1010141,1010142" openLevel="22" reward="10|100053=300000,10172=1;20|10173=3,10174=85,10172=1;30|100054=200,10174=160,10172=1" storyID="0" maxStar="30" nextID="101116" dungenonOrder="15" backID="101114" soundID="1031203"/>
<act pid="101116" name="乌鸡国（上）" nameIcon="TheFuBenUI|13" iconName="HeroItem|hero_110" backgroundName="TheFuBenUI_NoAlpha|point_03" desc="你猜" descName="——你猜" includeDungeon="1010143,1010144,1010145,1010146,1010147,1010148,1010149,1010150,1010151,1010152" openLevel="25" reward="10|100053=320000,10172=1;20|10173=3,10174=90,10172=1;30|100054=200,10174=170,10172=1" storyID="0" maxStar="30" nextID="101117" dungenonOrder="16" backID="101115" soundID="103199"/>
<act pid="101117" name="乌鸡国（中）" nameIcon="TheFuBenUI|14" iconName="HeroItem|hero_36" backgroundName="TheFuBenUI_NoAlpha|point_04" desc="你猜" descName="——你猜" includeDungeon="1010153,1010154,1010155,1010156,1010157,1010158,1010159,1010160,1010161,1010162" openLevel="28" reward="10|100053=340000,10172=1;20|10173=3,10174=95,10172=1;30|100054=200,10174=180,10172=1" storyID="0" maxStar="30" nextID="101118" dungenonOrder="17" backID="101116" soundID="1031204"/>
<act pid="101118" name="乌鸡国（下）" nameIcon="TheFuBenUI|15" iconName="HeroItem|hero_36" backgroundName="TheFuBenUI_NoAlpha|point_05" desc="你猜" descName="——你猜" includeDungeon="1010163,1010164,1010165,1010166,1010167,1010168,1010169,1010170,1010171,1010172" openLevel="31" reward="10|100053=360000,10172=1;20|10173=3,10174=100,10172=1;30|100054=200,10174=190,10172=1" storyID="0" maxStar="30" nextID="101119" dungenonOrder="18" backID="101117" soundID="1031201"/>
<act pid="101119" name="枯松涧（上）" nameIcon="TheFuBenUI|25" iconName="HeroItem|hero_39" backgroundName="TheFuBenUI_NoAlpha|point_01" desc="你猜" descName="——你猜" includeDungeon="1010173,1010174,1010175,1010176,1010177,1010178,1010179,1010180,1010181,1010182" openLevel="34" reward="10|100053=380000,10172=1;20|10173=3,10174=105,10172=1;30|100054=200,10174=200,10172=1" storyID="0" maxStar="30" nextID="101120" dungenonOrder="19" backID="101118" soundID="1031203"/>
<act pid="101120" name="枯松涧（中）" nameIcon="TheFuBenUI|26" iconName="HeroItem|hero_39" backgroundName="TheFuBenUI_NoAlpha|point_01" desc="你猜" descName="——你猜" includeDungeon="1010183,1010184,1010185,1010186,1010187,1010188,1010189,1010190,1010191,1010192" openLevel="37" reward="10|100053=400000,10172=1;20|10173=3,10174=110,10172=1;30|100054=200,10174=210,10172=1" storyID="0" maxStar="30" nextID="101121" dungenonOrder="20" backID="101119" soundID="103199"/>
<act pid="101121" name="枯松涧（下）" nameIcon="TheFuBenUI|27" iconName="HeroItem|hero_118" backgroundName="TheFuBenUI_NoAlpha|point_01" desc="你猜" descName="——你猜" includeDungeon="1010193,1010194,1010195,1010196,1010197,1010198,1010199,1010200,1010201,1010202" openLevel="40" reward="10|100053=420000,10172=1;20|10173=3,10174=115,10172=1;30|100054=200,10174=220,10172=1" storyID="0" maxStar="30" nextID="101122" dungenonOrder="21" backID="101120" soundID="1031204"/>
<act pid="101122" name="黑水河（上）" nameIcon="TheFuBenUI|16" iconName="HeroItem|hero_67" backgroundName="TheFuBenUI_NoAlpha|point_09" desc="你猜" descName="——你猜" includeDungeon="1010203,1010204,1010205,1010206,1010207,1010208,1010209,1010210,1010211,1010212" openLevel="43" reward="10|100053=440000,10172=1;20|10173=3,10174=120,10172=1;30|100054=200,10174=230,10172=1" storyID="0" maxStar="30" nextID="101123" dungenonOrder="22" backID="101121" soundID="1031201"/>
<act pid="101123" name="黑水河（中）" nameIcon="TheFuBenUI|17" iconName="HeroItem|monster_10" backgroundName="TheFuBenUI_NoAlpha|point_10" desc="你猜" descName="——你猜" includeDungeon="1010213,1010214,1010215,1010216,1010217,1010218,1010219,1010220,1010221,1010222" openLevel="46" reward="10|100053=460000,10172=1;20|10173=3,10174=125,10172=1;30|100054=200,10174=240,10172=1" storyID="0" maxStar="30" nextID="101124" dungenonOrder="23" backID="101122" soundID="1031203"/>
<act pid="101124" name="黑水河（下）" nameIcon="TheFuBenUI|18" iconName="HeroItem|monster_11" backgroundName="TheFuBenUI_NoAlpha|point_11" desc="你猜" descName="——你猜" includeDungeon="1010223,1010224,1010225,1010226,1010227,1010228,1010229,1010230,1010231,1010232" openLevel="49" reward="10|100053=480000,10172=1;20|10173=3,10174=130,10172=1;30|100054=200,10174=250,10172=1" storyID="0" maxStar="30" nextID="101125" dungenonOrder="24" backID="101123" soundID="103199"/>
<act pid="101125" name="车迟国（上）" nameIcon="TheFuBenUI|19" iconName="HeroItem|hero_117" backgroundName="TheFuBenUI_NoAlpha|point_12" desc="你猜" descName="——你猜" includeDungeon="1010233,1010234,1010235,1010236,1010237,1010238,1010239,1010240,1010241,1010242" openLevel="52" reward="10|100053=500000,10172=1;20|10173=3,10174=135,10172=1;30|100054=200,10174=260,10172=1" storyID="0" maxStar="30" nextID="101126" dungenonOrder="25" backID="101124" soundID="1031204"/>
<act pid="101126" name="车迟国（中）" nameIcon="TheFuBenUI|20" iconName="HeroItem|hero_145" backgroundName="TheFuBenUI_NoAlpha|point_01" desc="你猜" descName="——你猜" includeDungeon="1010243,1010244,1010245,1010246,1010247,1010248,1010249,1010250,1010251,1010252" openLevel="55" reward="10|100053=520000,10172=1;20|10173=3,10174=140,10172=1;30|100054=200,10174=270,10172=1" storyID="0" maxStar="30" nextID="101127" dungenonOrder="26" backID="101125" soundID="1031201"/>
<act pid="101127" name="车迟国（下）" nameIcon="TheFuBenUI|21" iconName="HeroItem|hero_61" backgroundName="TheFuBenUI_NoAlpha|point_02" desc="你猜" descName="——你猜" includeDungeon="1010253,1010254,1010255,1010256,1010257,1010258,1010259,1010260,1010261,1010262" openLevel="58" reward="10|100053=540000,10172=1;20|10173=3,10174=145,10172=1;30|100054=200,10174=280,10172=1" storyID="0" maxStar="30" nextID="0" dungenonOrder="27" backID="101126" soundID="1031203"/>
</root>
