<?xml version="1.0" encoding="UTF-8"?>
<root type="LikeabilityPrototype">
<lik pid="10331" property="100012,100013,100012,100011,100014,100012,100013,100012,100011,100014"/>
<lik pid="10332" property="100012,100013,100012,100011,100012,100011,100014,100011,100012,100011"/>
<lik pid="10333" property="100012,100014,100013,100012,100014,100011,100012,100014,100011,100014"/>
<lik pid="10334" property="100012,100013,100012,100011,100014,100012,100013,100012,100013,100011"/>
<lik pid="10335" property="100012,100013,100012,100011,100014,100012,100013,100012,100013,100011"/>
<lik pid="10336" property="100011,100012,100011,100013,100011,100014,100011,100012,100011,100011"/>
<lik pid="10337" property="100012,100014,100011,100012,100013,100012,100014,100011,100012,100014"/>
<lik pid="10338" property="100012,100013,100012,100011,100014,100012,100013,100012,100011,100014"/>
<lik pid="10339" property="100012,100013,100012,100011,100012,100013,100012,100014,100012,100014"/>
<lik pid="103310" property="100013,100014,100011,100012,100013,100014,100011,100012,100013,100014"/>
</root>
